cafex_desktop/__init__.py
cafex_desktop/desktop_client/__init__.py
cafex_desktop/desktop_client/desktop_application_handler.py
cafex_desktop/desktop_client/desktop_client_driver_initializer.py
cafex_desktop/desktop_client/desktop_client_exceptions.py
cafex_desktop/desktop_client/desktop_client_actions/__init__.py
cafex_desktop/desktop_client/desktop_client_actions/advanced_element_interactions.py
cafex_desktop/desktop_client/desktop_client_actions/base_desktop_client_actions.py
cafex_desktop/desktop_client/desktop_client_actions/desktop_element_interactions.py
cafex_desktop/desktop_client/desktop_client_actions/window_actions.py
cafex_desktop-1.0.0.dist-info/METADATA
cafex_desktop-1.0.0.dist-info/WHEEL
cafex_desktop-1.0.0.dist-info/entry_points.txt
cafex_desktop-1.0.0.dist-info/top_level.txt
cafex_desktop-1.0.0.dist-info/RECORD
