Metadata-Version: 2.4
Name: cafex-desktop
Version: 1.0.0
Summary: UI Library
Author-email: QA Automation Team <qa_automation@gmail.com>
Project-URL: Homepage, https://example.com
Project-URL: Documentation, https://readthedocs.org
Project-URL: Repository, https://github.com/me/spam.git
Project-URL: Issues, https://github.com/me/spam/issues
Project-URL: Changelog, https://github.com/me/spam/blob/master/CHANGELOG.md
Keywords: gui,pytest,automation,pywinauto
Classifier: Programming Language :: Python :: 3
Classifier: Operating System :: OS Independent
Requires-Python: >=3.12
Requires-Dist: cafex-core>=1.0.0
Requires-Dist: pywinauto==0.6.9; platform_system == "Windows"
